{
  "project_info": {
    "project_number": "455284561285",
    "firebase_url": "https://scsaplc.firebaseio.com",
    "project_id": "scsaplc",
    "storage_bucket": "scsaplc.appspot.com"
  },
  "client": [
    {
      "client_info": {
        "mobilesdk_app_id": "1:455284561285:android:7ec6f7bf26040afa",
        "android_client_info": {
          "package_name": "tw.com.scsa.scsaplc"
        }
      },
      "oauth_client": [
        {
          "client_id": "455284561285-gfcf0dd86ganbavr4fjs20ll4svi3njl.apps.googleusercontent.com",
          "client_type": 1,
          "android_info": {
            "package_name": "tw.com.scsa.scsaplc",
            "certificate_hash": "F9BDB33FEADEB2E491F896AD5F6204C6386143F6"
          }
        },
        {
          "client_id": "455284561285-tq66r03hberfksdnl981bf8ds9j9jbci.apps.googleusercontent.com",
          "client_type": 3
        }
      ],
      "api_key": [
        {
          "current_key": "AIzaSyBjhshwfyBB2Zo7fPqeuYMyaaQ-4o6TCh4"
        }
      ],
      "services": {
        "analytics_service": {
          "status": 1
        },
        "appinvite_service": {
          "status": 2,
          "other_platform_oauth_client": [
            {
              "client_id": "455284561285-tq66r03hberfksdnl981bf8ds9j9jbci.apps.googleusercontent.com",
              "client_type": 3
            }
          ]
        },
        "ads_service": {
          "status": 2
        }
      }
    },
    {
      "client_info": {
        "mobilesdk_app_id": "1:455284561285:android:f80f495d3c2d37bc",
        "android_client_info": {
          "package_name": "tw.com.scsa.newscsaplc"
        }
      },
      "oauth_client": [
        {
          "client_id": "455284561285-vr4j44mob8s1s2ndb6j16rpvkqv5dp66.apps.googleusercontent.com",
          "client_type": 1,
          "android_info": {
            "package_name": "tw.com.scsa.newscsaplc",
            "certificate_hash": "F9BDB33FEADEB2E491F896AD5F6204C6386143F6"
          }
        },
        {
          "client_id": "455284561285-tq66r03hberfksdnl981bf8ds9j9jbci.apps.googleusercontent.com",
          "client_type": 3d
        }
      ],
      "api_key": [
        {
          "current_key": "AIzaSyBjhshwfyBB2Zo7fPqeuYMyaaQ-4o6TCh4"
        }
      ],
      "services": {
        "analytics_service": {
          "status": 1
        },
        "appinvite_service": {
          "status": 2,
          "other_platform_oauth_client": [
            {
              "client_id": "455284561285-tq66r03hberfksdnl981bf8ds9j9jbci.apps.googleusercontent.com",
              "client_type": 3
            }
          ]
        },
        "ads_service": {
          "status": 2
        }
      }
    }
  ],
  "configuration_version": "1"
}